Metadata-Version: 2.1
Name: bio-hansel
Version: 2.6.1
Summary: Subtype microbial whole-genome sequencing (WGS) data using SNV targeting k-mer subtyping schemes.
Home-page: https://github.com/phac-nml/biohansel
Author: Peter Kruczkiewicz
Author-email: peter.kruczkiewicz@gmail.com
License: Apache Software License 2.0
Keywords: Salmonella enterica Heidelberg Enteritidis SNP kmer subtyping Aho-Corasick
Platform: UNKNOWN
Classifier: Development Status :: 5 - Production/Stable
Classifier: Environment :: Console
Classifier: Intended Audience :: Science/Research
Classifier: License :: OSI Approved :: Apache Software License
Classifier: Operating System :: POSIX :: Linux
Classifier: Programming Language :: Python :: 3 :: Only
Classifier: Programming Language :: Python :: 3.6
Classifier: Programming Language :: Python :: 3.7
Classifier: Programming Language :: Python :: 3.8
Classifier: Programming Language :: Python :: 3.9
Classifier: Programming Language :: Python :: Implementation :: CPython
Classifier: Topic :: Scientific/Engineering :: Bio-Informatics
Classifier: Topic :: Scientific/Engineering
Requires-Dist: numpy (>=1.12.1)
Requires-Dist: pandas (>=0.20.1)
Requires-Dist: pyahocorasick (>=1.1.6)
Requires-Dist: attrs
Requires-Dist: rich
